<Properties StartupConfiguration="{69853924-B7B8-4F3F-8706-0BC0799B84AE}|Default">
  <MonoDevelop.Ide.ItemProperties.BindingTest AndroidDesignerPreferredDevice="Nexus 4" PreferredExecutionTarget="Android.Android_Accelerated_Pie" />
  <MonoDevelop.Ide.Workbench ActiveDocument="Permutive.Xamarin.Android.Duktape/Transforms/EnumFields.xml">
    <Files>
      <File FileName="BindingTest/MainActivity.cs" Line="1" Column="1" />
      <File FileName="../../../../../Library/Frameworks/Mono.framework/External/xbuild/Xamarin/Android/Xamarin.Android.Common.targets" Line="2239" Column="57" />
      <File FileName="BindingTest/BindingTestApplication.cs" Line="1" Column="1" />
      <File FileName="BindingTest/Properties/AndroidManifest.xml" Line="1" Column="1" />
      <File FileName="Permutive.Xamarin.Android/Properties/AssemblyInfo.cs~" Line="1" Column="1" />
      <File FileName="Permutive.Xamarin.Android/Resources/Resource.designer.cs~" Line="1" Column="1" />
      <File FileName="Library.Android/Resources/values/Strings.xml" Line="1" Column="1" />
      <File FileName="Permutive.Xamarin.Android.Duktape/Transforms/Metadata.xml" Line="1" Column="1" />
      <File FileName="Permutive.Xamarin.Android.Duktape/Transforms/EnumMethods.xml" Line="1" Column="1" />
      <File FileName="Permutive.Xamarin.Android.Duktape/Transforms/EnumFields.xml" Line="1" Column="1" />
    </Files>
    <Pads>
      <Pad Id="ProjectPad">
        <State name="__root__">
          <Node name="Permutive.Xamarin" expanded="True">
            <Node name="Permutive.Xamarin.Android" expanded="True" />
            <Node name="Permutive.Xamarin.Android.Arch.Persistence.DB" expanded="True">
              <Node name="References" expanded="True" />
              <Node name="Packages" expanded="True" />
            </Node>
            <Node name="Permutive.Xamarin.Android.Arch.Persistence.DB.Framework" expanded="True" selected="True">
              <Node name="Packages" expanded="True" />
            </Node>
          </Node>
        </State>
      </Pad>
      <Pad Id="ClassPad">
        <State name="__root__">
          <Node name="Permutive.Xamarin" expanded="True" selected="True" />
        </State>
      </Pad>
      <Pad Id="MonoDevelop.Debugger.WatchPad">
        <State />
      </Pad>
    </Pads>
  </MonoDevelop.Ide.Workbench>
  <MonoDevelop.Ide.DebuggingService.PinnedWatches />
  <MonoDevelop.Ide.Workspace ActiveConfiguration="Release" />
  <MonoDevelop.Ide.DebuggingService.Breakpoints>
    <BreakpointStore />
  </MonoDevelop.Ide.DebuggingService.Breakpoints>
  <MultiItemStartupConfigurations />
</Properties>